mp3_to_mp4/__init__.py
mp3_to_mp4/__main__.py
mp3_to_mp4/cli.py
mp3_to_mp4/config.py
mp3_to_mp4/create_image.py
mp3_to_mp4/mp3_to_mp4.py
mp3_to_mp4/render.py
mp3_to_mp4/utils.py
mp3_to_mp4-0.2.0.dist-info/entry_points.txt
mp3_to_mp4-0.2.0.dist-info/LICENSE.md
mp3_to_mp4-0.2.0.dist-info/METADATA
mp3_to_mp4-0.2.0.dist-info/WHEEL
mp3_to_mp4-0.2.0.dist-info/RECORD
