Metadata-Version: 2.1
Name: mp3-to-mp4
Version: 0.2.0
Summary: A CLI application for converting audio files (.mp3, .wav, .flac, .aiff, etc) to mp4 file suitable for upload to social media sites like YouTube, Vimeo, etc.
Author: Henry Oberholtzer
Author-email: henryoberholtzer@gmail.com
Requires-Python: >=3.12,<3.13
Classifier: Development Status :: 4 - Beta
Classifier: Intended Audience :: End Users/Desktop
Classifier: License :: OSI Approved :: GNU General Public License v3 (GPLv3)
Classifier: Natural Language :: English
Classifier: Programming Language :: Python :: 3
Classifier: Programming Language :: Python :: 3.12
Classifier: Topic :: Multimedia :: Video :: Conversion
Requires-Dist: moviepy (>=1.0.3,<2.0.0)
Requires-Dist: pyinstaller (>=6.5.0,<7.0.0)
Requires-Dist: pytest (>=8.1.1,<9.0.0)
Requires-Dist: pytest-cov (>=4.1.0,<5.0.0)
Requires-Dist: pytest-mock (>=3.12.0,<4.0.0)
Requires-Dist: tinytag (>=1.10.1,<2.0.0)
Requires-Dist: typer[all] (>=0.9.0,<0.10.0)
